ahri_mime/MIME.py
ahri_mime/__init__.py
ahri_mime/handle.py
ahri_mime-0.0.1.dist-info/LICENSE
ahri_mime-0.0.1.dist-info/METADATA
ahri_mime-0.0.1.dist-info/WHEEL
ahri_mime-0.0.1.dist-info/top_level.txt
ahri_mime-0.0.1.dist-info/RECORD
