Metadata-Version: 2.1
Name: ahri-mime
Version: 0.0.1
Summary: ahri mime
Home-page: https://github.com/fox-ahri
Author: ahri
Author-email: ahriknow@gmail.com
License: MIT Licence
Keywords: ahri,python,pip,mime
Platform: any
Classifier: Development Status :: 3 - Alpha
Classifier: Intended Audience :: Developers
Classifier: Operating System :: OS Independent
Classifier: Programming Language :: Python :: 3
Classifier: Programming Language :: Python :: 3.5
Classifier: Programming Language :: Python :: 3.6
Classifier: Programming Language :: Python :: 3.7
Classifier: Programming Language :: Python :: 3.8
Classifier: Programming Language :: Python :: 3.9
Classifier: License :: OSI Approved :: MIT License
Requires-Python: >=3.5.0
